i2ssh/__init__.py
i2ssh/applescript.py
i2ssh/config.py
i2ssh/layout.py
i2ssh/main.py
i2ssh/window.py
i2ssh-0.4.0.dist-info/DESCRIPTION.rst
i2ssh-0.4.0.dist-info/entry_points.txt
i2ssh-0.4.0.dist-info/METADATA
i2ssh-0.4.0.dist-info/metadata.json
i2ssh-0.4.0.dist-info/RECORD
i2ssh-0.4.0.dist-info/top_level.txt
i2ssh-0.4.0.dist-info/WHEEL
tests/__init__.py
tests/applescript_test.py
tests/config_test.py
tests/layout_test.py
tests/window_test.py
