Metadata-Version: 2.0
Name: i2ssh
Version: 0.4.0
Summary: SSH into to a cluster of machines using iTerm 2 split panes on OSX.
Home-page: https://github.com/mbruggmann/i2ssh
Author: Marc Bruggmann
Author-email: bruggmann.marc@gmail.com
License: Apache License 2.0
Platform: UNKNOWN
Classifier: Topic :: Utilities
Classifier: Programming Language :: Python
Classifier: Operating System :: MacOS
Requires-Dist: pyyaml
Requires-Dist: quik
Requires-Dist: pyobjc-framework-Cocoa
